datamakerkpanger882/__init__.py
datamakerkpanger882/data.py
datamakerkpanger882-0.0.3.dist-info/LICENSE
datamakerkpanger882-0.0.3.dist-info/METADATA
datamakerkpanger882-0.0.3.dist-info/WHEEL
datamakerkpanger882-0.0.3.dist-info/top_level.txt
datamakerkpanger882-0.0.3.dist-info/RECORD
